LycorisAD.py
LycorisAD-1.0.2.dist-info/LICENSE
LycorisAD-1.0.2.dist-info/METADATA
LycorisAD-1.0.2.dist-info/WHEEL
LycorisAD-1.0.2.dist-info/top_level.txt
LycorisAD-1.0.2.dist-info/RECORD
