Metadata-Version: 2.1
Name: LycorisAD
Version: 1.0.2
Summary: An elegant outlier detection algorithm framework based on AutoEncoder.
Home-page: https://github.com/RootHarold/LycorisAD
Author: RootHarold
Author-email: rootharold@163.com
License: UNKNOWN
Platform: UNKNOWN
Requires-Dist: LycorisNet (>=2.5)
Requires-Dist: deap (>=1.3)
Requires-Dist: scipy (>=1.3)
Requires-Dist: numpy (>=1.18)
